NAME/__init__.py
NAME/hello.py
tests/NAME_tests.py
tests/__init__.py
skeleton_project_name_tests-1.0.1.1.dist-info/LICENSE
skeleton_project_name_tests-1.0.1.1.dist-info/METADATA
skeleton_project_name_tests-1.0.1.1.dist-info/WHEEL
skeleton_project_name_tests-1.0.1.1.dist-info/top_level.txt
skeleton_project_name_tests-1.0.1.1.dist-info/RECORD
