Metadata-Version: 2.1
Name: skeleton-project-name-tests
Version: 1.0.1.1
Summary: A sample My Project
Home-page: 
Author: zhangxianggang73
Author-email: zhangxianggang73@sina.com
Classifier: Programming Language :: Python :: 3
Classifier: License :: OSI Approved :: MIT License
Classifier: Operating System :: OS Independent
Requires-Python: >=3.7
License-File: LICENSE
Requires-Dist: nose
